llama_index/indices/managed/google/__init__.py
llama_index/indices/managed/google/base.py
llama_index_indices_managed_google-0.4.1.dist-info/METADATA
llama_index_indices_managed_google-0.4.1.dist-info/WHEEL
llama_index_indices_managed_google-0.4.1.dist-info/licenses/LICENSE
llama_index_indices_managed_google-0.4.1.dist-info/RECORD
