Metadata-Version: 2.4
Name: llama-index-indices-managed-google
Version: 0.4.1
Summary: llama-index managed google integration
Author-email: Your Name <you@example.com>
License-Expression: MIT
License-File: LICENSE
Requires-Python: <4.0,>=3.9
Requires-Dist: llama-index-core<0.15,>=0.13.0
Requires-Dist: llama-index-response-synthesizers-google<0.5,>=0.4.0
Requires-Dist: llama-index-vector-stores-google<0.5,>=0.4.0
